chem_bench-0.1.0.dist-info/METADATA
chem_bench-0.1.0.dist-info/WHEEL
chem_bench-0.1.0.dist-info/licenses/LICENSE
chembench/.langchain.db
chembench/__init__.py
chembench/analysis.py
chembench/baseline.py
chembench/classification.py
chembench/constant.py
chembench/evaluate.py
chembench/helper.py
chembench/metrics.py
chembench/prompter.py
chembench/report.py
chembench/settings.py
chembench/task.py
chembench/types.py
chembench/utils.py
chembench/watermark.py
chem_bench-0.1.0.dist-info/RECORD
