Metadata-Version: 2.1
Name: chem-bench
Version: 0.1.0
Summary: Benchmark chemistry performance of LLMs
Author-Email: Kevin Maik Jablonka <mail@kjablonka.com>
License: MIT
Requires-Python: >=3.10
Requires-Dist: langchain>=0.1.5
Requires-Dist: fastcore>=1.5.29
Requires-Dist: cohere>=4.45
Requires-Dist: scikit-learn>=1.4.0
Requires-Dist: matplotlib>=3.8.2
Requires-Dist: plotly>=5.18.0
Requires-Dist: loguru>=0.7.2
Requires-Dist: tqdm>=4.66.1
Requires-Dist: pint>=0.23
Requires-Dist: openai>=1.11.1
Requires-Dist: pandas>=2.2.0
Requires-Dist: python-dotenv>=1.0.1
Requires-Dist: transformers>=4.37.2
Requires-Dist: accelerate>=0.26.1
Requires-Dist: fire>=0.5.0
Requires-Dist: anthropic>=0.15.0
Requires-Dist: langchain-google-genai>=0.0.6
Requires-Dist: langchain-openai>=0.0.5
Requires-Dist: langchain-community>=0.0.17
Requires-Dist: langchainhub>=0.1.14
Requires-Dist: langchain-experimental>=0.0.50
Requires-Dist: duckduckgo-search>=4.2
Requires-Dist: wolframalpha>=5.0.0
